flask_quick/__init__.py
flask_quick/forms.py
flask_quick/views.py
flask_quick/exceptions/__init__.py
flask_quick/exceptions/api.py
flask_quick/lib/__init__.py
flask_quick/lib/bootstrap.py
flask_quick/lib/extensions.py
flask_quick/utils/__init__.py
flask_quick/utils/json.py
python_flask_quick_start-1.4.dist-info/LICENSE
python_flask_quick_start-1.4.dist-info/METADATA
python_flask_quick_start-1.4.dist-info/WHEEL
python_flask_quick_start-1.4.dist-info/top_level.txt
python_flask_quick_start-1.4.dist-info/RECORD
