Metadata-Version: 2.1
Name: python-flask-quick-start
Version: 1.4
Summary: An python3 flask web framework template.
Home-page: UNKNOWN
Author: datochan
Author-email: datochan@qq.com
License: MIT
Platform: UNKNOWN
License-File: LICENSE
Requires-Dist: Flask (==2.2.3)
Requires-Dist: Flask-HTTPAuth (==4.7.0)
Requires-Dist: Flask-Login (==0.6.2)
Requires-Dist: Flask-Migrate (==4.0.4)
Requires-Dist: Flask-Principal (==0.4.0)
Requires-Dist: Flask-Security (==3.0.0)
Requires-Dist: Flask-SQLAlchemy (==3.0.3)
Requires-Dist: PyMySQL (==1.0.2)
Requires-Dist: SQLAlchemy (==2.0.4)
